mcp_smarthub/__init__.py
mcp_smarthub/config.py
mcp_smarthub/server.py
mcp_smarthub/types.py
mcp_smarthub/cli/__init__.py
mcp_smarthub/cli/main.py
mcp_smarthub/utils/__init__.py
mcp_smarthub/utils/snowflake_utils.py
mcp_smarthub-0.2.9.dist-info/licenses/LICENSE
mcp_smarthub-0.2.9.dist-info/METADATA
mcp_smarthub-0.2.9.dist-info/WHEEL
mcp_smarthub-0.2.9.dist-info/entry_points.txt
mcp_smarthub-0.2.9.dist-info/top_level.txt
mcp_smarthub-0.2.9.dist-info/RECORD
