Metadata-Version: 2.4
Name: mcp-smarthub
Version: 0.2.9
Summary: SmartHub MCP extension for Goose
Author-email: Block <goose@squareup.com>
License-Expression: MIT
Project-URL: Homepage, https://github.com/squareup/smarthub-extension
Project-URL: Documentation, https://block.github.io/goose/docs/tutorials/custom-extensions
Requires-Python: >=3.10
License-File: LICENSE
Requires-Dist: mcp>=1.4.1
Requires-Dist: snowflake-connector-python>=3.14.0
Requires-Dist: uvicorn>=0.34.0
Requires-Dist: fastapi>=0.109.0
Requires-Dist: typing-extensions>=4.9.0
Dynamic: license-file
